squarelet_auth/__init__.py
squarelet_auth/apps.py
squarelet_auth/backends.py
squarelet_auth/fields.py
squarelet_auth/mixins.py
squarelet_auth/pipeline.py
squarelet_auth/settings.py
squarelet_auth/tasks.py
squarelet_auth/urls.py
squarelet_auth/utils.py
squarelet_auth/views.py
squarelet_auth/migrations/__init__.py
squarelet_auth/organizations/__init__.py
squarelet_auth/organizations/admin.py
squarelet_auth/organizations/apps.py
squarelet_auth/organizations/models.py
squarelet_auth/organizations/urls.py
squarelet_auth/organizations/utils.py
squarelet_auth/organizations/views.py
squarelet_auth/organizations/migrations/0001_initial.py
squarelet_auth/organizations/migrations/0002_auto_20200423_1008.py
squarelet_auth/organizations/migrations/0003_plan_resources.py
squarelet_auth/organizations/migrations/0004_auto_20200527_0920.py
squarelet_auth/organizations/migrations/0005_auto_20200527_0921.py
squarelet_auth/organizations/migrations/0006_auto_20200527_1646.py
squarelet_auth/organizations/migrations/0007_delete_plan.py
squarelet_auth/organizations/migrations/0008_alter_entitlement_resources.py
squarelet_auth/organizations/migrations/0009_organization_merged.py
squarelet_auth/organizations/migrations/0010_organization_members_organization_parent_and_more.py
squarelet_auth/organizations/migrations/__init__.py
squarelet_auth/users/__init__.py
squarelet_auth/users/admin.py
squarelet_auth/users/models.py
squarelet_auth/users/utils.py
squarelet_auth-0.1.14.dist-info/LICENSE
squarelet_auth-0.1.14.dist-info/METADATA
squarelet_auth-0.1.14.dist-info/WHEEL
squarelet_auth-0.1.14.dist-info/top_level.txt
squarelet_auth-0.1.14.dist-info/RECORD
