Metadata-Version: 2.1
Name: squarelet-auth
Version: 0.1.14
Summary: Django authentication against the MuckRock user service
Home-page: https://github.com/muckrock/squarelet-auth/
Author: Mitchell Kotler
Author-email: mitch@muckrock.com
License: UNKNOWN
Platform: UNKNOWN
Classifier: Programming Language :: Python :: 3
Classifier: License :: OSI Approved :: BSD License
Classifier: Operating System :: OS Independent
Requires-Python: >=3.6
License-File: LICENSE
Requires-Dist: celery
Requires-Dist: django
Requires-Dist: requests
Requires-Dist: social-auth-core[openidconnect]
